google_trans_lzx-0.0.3.data/scripts/translate
googletrans/__init__.py
googletrans/client.py
googletrans/constants.py
googletrans/gtoken.py
googletrans/models.py
googletrans/urls.py
googletrans/utils.py
google_trans_lzx-0.0.3.dist-info/LICENSE
google_trans_lzx-0.0.3.dist-info/METADATA
google_trans_lzx-0.0.3.dist-info/WHEEL
google_trans_lzx-0.0.3.dist-info/top_level.txt
google_trans_lzx-0.0.3.dist-info/RECORD
